odoo10_addon_sale_layout_hidden-10.0.1.0.2-py3.8-nspkg.pth
odoo/addons/sale_layout_hidden/README.rst
odoo/addons/sale_layout_hidden/__init__.py
odoo/addons/sale_layout_hidden/__manifest__.py
odoo/addons/sale_layout_hidden/i18n/ar.po
odoo/addons/sale_layout_hidden/i18n/bg.po
odoo/addons/sale_layout_hidden/i18n/bs.po
odoo/addons/sale_layout_hidden/i18n/ca.po
odoo/addons/sale_layout_hidden/i18n/cs.po
odoo/addons/sale_layout_hidden/i18n/de.po
odoo/addons/sale_layout_hidden/i18n/el_GR.po
odoo/addons/sale_layout_hidden/i18n/en_GB.po
odoo/addons/sale_layout_hidden/i18n/es.po
odoo/addons/sale_layout_hidden/i18n/es_CR.po
odoo/addons/sale_layout_hidden/i18n/es_EC.po
odoo/addons/sale_layout_hidden/i18n/es_ES.po
odoo/addons/sale_layout_hidden/i18n/es_MX.po
odoo/addons/sale_layout_hidden/i18n/es_VE.po
odoo/addons/sale_layout_hidden/i18n/et.po
odoo/addons/sale_layout_hidden/i18n/fi.po
odoo/addons/sale_layout_hidden/i18n/fr.po
odoo/addons/sale_layout_hidden/i18n/fr_CA.po
odoo/addons/sale_layout_hidden/i18n/fr_CH.po
odoo/addons/sale_layout_hidden/i18n/gl.po
odoo/addons/sale_layout_hidden/i18n/hr.po
odoo/addons/sale_layout_hidden/i18n/hr_HR.po
odoo/addons/sale_layout_hidden/i18n/hu.po
odoo/addons/sale_layout_hidden/i18n/id.po
odoo/addons/sale_layout_hidden/i18n/it.po
odoo/addons/sale_layout_hidden/i18n/ja.po
odoo/addons/sale_layout_hidden/i18n/lt.po
odoo/addons/sale_layout_hidden/i18n/mk.po
odoo/addons/sale_layout_hidden/i18n/mn.po
odoo/addons/sale_layout_hidden/i18n/nb.po
odoo/addons/sale_layout_hidden/i18n/nb_NO.po
odoo/addons/sale_layout_hidden/i18n/nl.po
odoo/addons/sale_layout_hidden/i18n/nl_BE.po
odoo/addons/sale_layout_hidden/i18n/nl_NL.po
odoo/addons/sale_layout_hidden/i18n/pl.po
odoo/addons/sale_layout_hidden/i18n/pt.po
odoo/addons/sale_layout_hidden/i18n/pt_BR.po
odoo/addons/sale_layout_hidden/i18n/pt_PT.po
odoo/addons/sale_layout_hidden/i18n/ro.po
odoo/addons/sale_layout_hidden/i18n/ru.po
odoo/addons/sale_layout_hidden/i18n/sale_layout_hidden.pot
odoo10_addon_sale_layout_hidden-10.0.1.0.2.dist-info/METADATA
odoo10_addon_sale_layout_hidden-10.0.1.0.2.dist-info/WHEEL
odoo10_addon_sale_layout_hidden-10.0.1.0.2.dist-info/namespace_packages.txt
odoo10_addon_sale_layout_hidden-10.0.1.0.2.dist-info/top_level.txt
odoo10_addon_sale_layout_hidden-10.0.1.0.2.dist-info/RECORD
